hardware/ip_repo/EdXel_1.1/EdXel_v1_1_project/EdXel_v1_1_project.srcs/sources_1/new/DummyEPU.v
`timescale 1ns / 1ps
//////////////////////////////////////////////////////////////////////////////////
// Company: 
// Engineer: 
// 
// Create Date: 11/13/2014 09:02:42 PM
// Design Name: 
// Module Name: DummyEPU
// Project Name: 
// Target Devices: 
// Tool Versions: 
// Description: 
// 
// Dependencies: 
// 
// Revision:
// Revision 0.01 - File Created
// Additional Comments:
// 
//////////////////////////////////////////////////////////////////////////////////

//Dummy EPU. if signature minus key equals message, it is valid, otherwise invalid

module DummyEPU(
    input [511:0] signature,
    input [255:0] key,
    input [255:0] message,
    output ready,
    input valid,
    output result,
    input resetn,
    input clk
    );

reg [511:0] iresult;    
reg rresult;
reg rready;

assign ready = rready;
assign result = rresult;

always @ (posedge clk)
if (resetn == 0) begin
    iresult <= 512'b0;
    rready <= 1'b1;
    rresult <= 1'b0;
end else if (valid == 1 && rready == 1) begin
    iresult <= signature;
    rready <= 0;
    rresult <= rresult;
end else if (rready == 0) begin
    rresult <= signature[7:0] == 8'h55;
    rready <= 1;
    iresult <= iresult;
end
    
endmodule

hardware/ip_repo/EdXel_1.1/EdXel_v1_1_project/EdXel_v1_1_project.srcs/sim_1/new/DummyEPU_tb.v
`timescale 1ns / 1ps
//////////////////////////////////////////////////////////////////////////////////
// Company: 
// Engineer: 
// 
// Create Date: 11/13/2014 09:17:44 PM
// Design Name: 
// Module Name: DummyEPU_tb
// Project Name: 
// Target Devices: 
// Tool Versions: 
// Description: 
// 
// Dependencies: 
// 
// Revision:
// Revision 0.01 - File Created
// Additional Comments:
// 
//////////////////////////////////////////////////////////////////////////////////


module DummyEPU_tb(

    );
    reg clk, reset;
    reg [511:0] sig;
    reg [255:0] key;
    reg [255:0] m;
    reg valid;
    wire ready, result;
    DummyEPU EPU0 (
        .clk(clk),
        .resetn(reset),
        .signature(sig),
        .key(key),
        .message(m),
        .ready(ready),
        .result(result),
        .valid(valid)
    );
    
    initial
    begin
        $display("Starting");
        sig = 0;
        key = 0;
        m = 0;
        valid = 0;
        reset = 1;
        clk = 0;
        #10 reset = 0;
        #20 reset = 1;
            while(!ready);
            sig = 512'hDEAD;
            key = 256'hDE00;
            m = 256'h00AD;
        #10
            valid = 1;
        #10
            valid = 0;
        #50    
            //while(!ready);
            sig = 512'hDEAD;
            key = 256'hDE01;
            m = 256'h00AD;
        #10
            valid = 1;
        #10
            valid = 0;
            
    end
    
    initial begin
        $dumpfile("EPU.vcd");
        $dumpvars;
    end
    
    initial
    #300 $finish;
    
    always
        #5 clk = !clk;
        
endmodule

hardware/ip_repo/EdXel_1.1/EdXel_v1_1_project/EdXel_v1_1_project.sim/sim_1/behav/EPU.vcd
$date
   Thu Nov 13 22:11:15 2014
$end
$version
  13.1
$end
$timescale
  1ps
$end
$scope module DummyEPU_tb $end
$var reg 1 ! clk $end
$var reg 1 " reset $end
$var reg 512 # sig [511:0] $end
$var reg 256 $ key [255:0] $end
$var reg 256 % m [255:0] $end
$var reg 1 & valid $end
$var wire 1 ' ready $end
$var wire 1 ( result $end
$scope module EPU0 $end
$var wire 512 ) signature [511:0] $end
$var wire 256 * key [255:0] $end
$var wire 256 + message [255:0] $end
$var wire 1 , ready $end
$var wire 1 - valid $end
$var wire 1 . result $end
$var wire 1 / resetn $end
$var wire 1 0 clk $end
$var reg 512 1 iresult [511:0] $end
$var reg 1 2 rresult $end
$var reg 1 3 rready $end
$upscope $end
$upscope $end
$enddefinitions $end
#0
$dumpvars
0!
1"
b0 #
b0 $
b0 %
0&
x'
x(
b0 )
b0 *
b0 +
x,
0-
x.
1/
00
bx 1
x2
x3
$end
#5000
1!
10
#10000
0!
0"
0/
00
#15000
1!
1'
1,
10
b0 1
13
#20000
0!
00
#25000
1!
10
#30000
0!
1"
b1101111010101101 #
b1101111000000000 $
b10101101 %
b1101111010101101 )
b1101111000000000 *
b10101101 +
1/
00
#35000
1!
10
#40000
0!
1&
1-
00
#45000
1!
0'
0,
10
b10101101 1
03
#50000
0!
0&
0-
00
#55000
1!
1'
1(
1,
1.
10
12
13
#60000
0!
00
#65000
1!
10
#70000
0!
00
#75000
1!
10
#80000
0!
00
#85000
1!
10
#90000
0!
00
#95000
1!
10
#100000
0!
b1101111000000001 $
b1101111000000001 *
00
#105000
1!
10
#110000
0!
1&
1-
00
#115000
1!
0'
0,
10
b10101100 1
03
#120000
0!
0&
0-
00
#125000
1!
1'
0(
1,
0.
10
02
13
